foxops/__init__.py
foxops/__main__.py
foxops/database/__init__.py
foxops/database/engine.py
foxops/database/repositories/__init__.py
foxops/database/repositories/change/__init__.py
foxops/database/repositories/change/errors.py
foxops/database/repositories/change/model.py
foxops/database/repositories/change/repository.py
foxops/database/repositories/incarnation/__init__.py
foxops/database/repositories/incarnation/errors.py
foxops/database/repositories/incarnation/model.py
foxops/database/repositories/incarnation/repository.py
foxops/database/schema.py
foxops/dependencies.py
foxops/engine/__init__.py
foxops/engine/__main__.py
foxops/engine/custom_filters.py
foxops/engine/errors.py
foxops/engine/initialization.py
foxops/engine/models/__init__.py
foxops/engine/models/incarnation_state.py
foxops/engine/models/template_config.py
foxops/engine/patching/__init__.py
foxops/engine/patching/git_diff_patch.py
foxops/engine/rendering.py
foxops/engine/update.py
foxops/error_handlers.py
foxops/errors.py
foxops/external/__init__.py
foxops/external/git.py
foxops/hosters/__init__.py
foxops/hosters/gitlab.py
foxops/hosters/local.py
foxops/hosters/types.py
foxops/logger.py
foxops/middlewares.py
foxops/models/__init__.py
foxops/models/change.py
foxops/models/errors.py
foxops/models/incarnation.py
foxops/openapi.py
foxops/routers/__init__.py
foxops/routers/auth.py
foxops/routers/changes.py
foxops/routers/incarnations.py
foxops/routers/not_found.py
foxops/routers/version.py
foxops/services/__init__.py
foxops/services/change.py
foxops/services/incarnation.py
foxops/settings.py
foxops/utils.py
foxops-2.6.0.dist-info/METADATA
foxops-2.6.0.dist-info/WHEEL
foxops-2.6.0.dist-info/entry_points.txt
foxops-2.6.0.dist-info/licenses/LICENSE
foxops-2.6.0.dist-info/RECORD
