Metadata-Version: 2.4
Name: foxops
Version: 2.6.0
Summary: Foxops 🦊
License: Apache-2.0
License-File: LICENSE
Author: Alexander Hungenberg
Author-email: alexander.hungenberg@roche.com
Requires-Python: >=3.12,<3.13
Classifier: License :: OSI Approved :: Apache Software License
Classifier: Programming Language :: Python :: 3
Classifier: Programming Language :: Python :: 3.12
Requires-Dist: Jinja2 (>=3.0.3,<4.0.0)
Requires-Dist: SQLAlchemy[asyncio] (>=2.0.2,<3.0.0)
Requires-Dist: aiopath (>=0.7.7,<0.8.0)
Requires-Dist: aiosqlite (>=0.20.0,<0.21.0)
Requires-Dist: alembic[tz] (>=1.8.1,<2.0.0)
Requires-Dist: asyncpg (>=0.29.0,<0.30.0)
Requires-Dist: fastapi (>=0.120.1)
Requires-Dist: greenlet (>=3.1.1,<4.0.0)
Requires-Dist: httpx (>=0.27.2,<0.28.0)
Requires-Dist: pydantic (>=2.11.7,<3.0.0)
Requires-Dist: pydantic-settings (==2.10.1)
Requires-Dist: rich (>=14.1.0,<15.0.0)
Requires-Dist: ruamel.yaml (>=0.17.20,<0.18.0)
Requires-Dist: starlette (==0.49.3)
Requires-Dist: structlog (==25.5.0)
Requires-Dist: tenacity (>=9.0.0,<10.0.0)
Requires-Dist: typer (==0.16.0)
Requires-Dist: uvicorn (==0.38.0)
